lsyflaskmicroapp_video/__init__.py
lsyflaskmicroapp_video/orm.py
lsyflaskmicroapp_video/apis/__init__.py
lsyflaskmicroapp_video/apis/st_video_b.py
lsyflaskmicroapp_video/apis/st_video_group_b.py
lsyflaskmicroapp_video/apis/st_video_image_r.py
lsyflaskmicroapp_video/entitys/__init__.py
lsyflaskmicroapp_video/entitys/st_video_b.py
lsyflaskmicroapp_video/entitys/st_video_group_b.py
lsyflaskmicroapp_video/entitys/st_video_image_r.py
lsyflaskmicroapp_video/models/__init__.py
lsyflaskmicroapp_video/models/st_video_b.py
lsyflaskmicroapp_video/models/st_video_group_b.py
lsyflaskmicroapp_video/models/st_video_image_r.py
lsyflaskmicroapp_video/schemas/__init__.py
lsyflaskmicroapp_video/schemas/st_video_b.py
lsyflaskmicroapp_video/schemas/st_video_group_b.py
lsyflaskmicroapp_video/schemas/st_video_image_r.py
lsyflaskmicroapp_video-1.0.0.dist-info/METADATA
lsyflaskmicroapp_video-1.0.0.dist-info/WHEEL
lsyflaskmicroapp_video-1.0.0.dist-info/top_level.txt
lsyflaskmicroapp_video-1.0.0.dist-info/RECORD
